{
    "Test Fav List One": [
        {
            "name": "Toronto",
            "country": "Canada",
            "rating": 4,
            "imagePath": "images/toronto.jpeg"
        },
        {
            "name": "Vancouver",
            "country": "Canada",
            "rating": 5,
            "imagePath": "images/vancouver.jpeg",

        }
    ],
    "Test Fav List Two": [
        {
            "name": "New York",
            "country": "USA",
            "rating": 5,
            "imagePath": "images/nyc.jpeg"
        },
        {
            "name": "Los Angeles",
            "country": "USA",
            "rating": 3,
            "imagePath": "images/la.jpeg"
        }
    ]
}
